django_response_helpers-3.0.1.dist-info/licenses/LICENSE
response_helpers/__init__.py
response_helpers/helpers.py
response_helpers/http.py
response_helpers/models.py
response_helpers/views.py
response_helpers/tests/__init__.py
response_helpers/tests/test_helpers.py
response_helpers/tests/test_http.py
response_helpers/tests/test_views.py
django_response_helpers-3.0.1.dist-info/METADATA
django_response_helpers-3.0.1.dist-info/WHEEL
django_response_helpers-3.0.1.dist-info/top_level.txt
django_response_helpers-3.0.1.dist-info/RECORD
